[
  {
    "id": 92427,
    "date": "06.09.2026",
    "company": "Transocean",
    "rig": "TNG",
    "whatWasSeen": "Observed gate into well test from staircase BB was correctly hung up and labeled . But left in open position.",
    "whatWasDiscussed": "Contacted one of the workers in the area and asked him to check occasionally that the gate was in closed position.",
    "whatWasReinforced": "",
    "commentsAddedByRigLeadership": ""
  },
  {
    "id": 92428,
    "date": "06.09.2026",
    "company": "Transocean",
    "rig": "TNG",
    "whatWasSeen": "mange sperringer på dekket",
    "whatWasDiscussed": "viktig at folk ikke spør om å passere sperringer .slik at det ikke blir så mye spørsmål på radio",
    "whatWasReinforced": "finn en ny rute",
    "commentsAddedByRigLeadership": "God praksis å bruke 1 minutt ekstra på alternativ rute kontra å bryte inn i pågående operasjon med mindre det er helt nødvendig. Ch.M"
  },
  {
    "id": 92429,
    "date": "06.09.2026",
    "company": "oceaneering",
    "rig": "TNG",
    "whatWasSeen": "Bruker korteste vei til og fra rov og dobbelt hørselsvern",
    "whatWasDiscussed": "",
    "whatWasReinforced": "",
    "commentsAddedByRigLeadership": "Helt ihht Daily HSE Focus. Ch.M"
  },
  {
    "id": 92430,
    "date": "06.09.2026",
    "company": "Transocean",
    "rig": "TNG",
    "whatWasSeen": "Fått flere observasjoner fra Egon denne turen på ting han observerer som og gir beskjed om at ikke er som det skal.",
    "whatWasDiscussed": "Flott gjort å få med seg små detaljer som mange passerer og i tillegg ta eierskap og melde inn",
    "whatWasReinforced": "Bra egenskap og holdning !",
    "commentsAddedByRigLeadership": ""
  },
  {
    "id": 92431,
    "date": "06.09.2026",
    "company": "Harbour",
    "rig": "TNG",
    "whatWasSeen": "Joined the medic while changing the eyewash bottles in the pontoon area to help familiarize him with the rig and its layout.",
    "whatWasDiscussed": "",
    "whatWasReinforced": "",
    "commentsAddedByRigLeadership": ""
  },
  {
    "id": 92432,
    "date": "06.09.2026",
    "company": "oceaneering",
    "rig": "TNG",
    "whatWasSeen": "Vanntett dør etterlatt åpen ved utgang av garderobe",
    "whatWasDiscussed": "",
    "whatWasReinforced": "",
    "commentsAddedByRigLeadership": "Viktig at alle dører holdes lukket, da de er en viktig del av våre integritets barrierer. Det seg være vanntett, brann eller værtette dører. Ch.M"
  },
  {
    "id": 92433,
    "date": "06.09.2026",
    "company": "Transocean",
    "rig": "TNG",
    "whatWasSeen": "100 Års Jubileum",
    "whatWasDiscussed": "Særdes velsmakende og godt måltid i forbindelse med 100 års jubileum",
    "whatWasReinforced": "Gikk innom Stuert og fortalte han at det var bra.",
    "commentsAddedByRigLeadership": ""
  },
  {
    "id": 92434,
    "date": "06.09.2026",
    "company": "Aramark",
    "rig": "TNG",
    "whatWasSeen": "Nytt rengjørings kjemikalie. Leste databladet og satte meg inn i hvordan å bruke det",
    "whatWasDiscussed": "",
    "whatWasReinforced": "",
    "commentsAddedByRigLeadership": ""
  },
  {
    "id": 92435,
    "date": "06.09.2026",
    "company": "Aramark",
    "rig": "TNG",
    "whatWasSeen": "Verktøy i lomma",
    "whatWasDiscussed": "",
    "whatWasReinforced": "",
    "commentsAddedByRigLeadership": ""
  },
  {
    "id": 92436,
    "date": "06.09.2026",
    "company": "oceaneering",
    "rig": "TNG",
    "whatWasSeen": "Så catering crew putte opp skilt ved vasking av garderober",
    "whatWasDiscussed": "",
    "whatWasReinforced": "",
    "commentsAddedByRigLeadership": ""
  },
  {
    "id": 92437,
    "date": "06.09.2026",
    "company": "Baker Hughes",
    "rig": "TNG",
    "whatWasSeen": "Pro pt kort og vakt ved overføring til skip.",
    "whatWasDiscussed": "",
    "whatWasReinforced": "",
    "commentsAddedByRigLeadership": ""
  },
  {
    "id": 92438,
    "date": "06.09.2026",
    "company": "Transocean",
    "rig": "TNG",
    "whatWasSeen": "gikk runde i ansvarsområde og sjekket lastebærere for løse gjenstander, men fant ingen",
    "whatWasDiscussed": ".",
    "whatWasReinforced": "fortsette senere...",
    "commentsAddedByRigLeadership": ""
  },
  {
    "id": 92439,
    "date": "06.09.2026",
    "company": "rtc",
    "rig": "TNG",
    "whatWasSeen": "Ryddet i lift på riserdekk og fjernet verktøy vi ikke hadde bruk for mer",
    "whatWasDiscussed": "",
    "whatWasReinforced": "",
    "commentsAddedByRigLeadership": ""
  },
  {
    "id": 92440,
    "date": "06.09.2026",
    "company": "Wellpartner",
    "rig": "TNG",
    "whatWasSeen": "Tok ein PDO runde i Derrick",
    "whatWasDiscussed": "Derrick fremstår som ryddig og ingen",
    "whatWasReinforced": "",
    "commentsAddedByRigLeadership": ""
  },
  {
    "id": 92441,
    "date": "06.09.2026",
    "company": "rtc",
    "rig": "TNG",
    "whatWasSeen": "DROP SJEKK",
    "whatWasDiscussed": "rPyDddOig fhuentnet.",
    "whatWasReinforced": "Holde orden",
    "commentsAddedByRigLeadership": ""
  },
  {
    "id": 92442,
    "date": "06.09.2026",
    "company": "Transocean",
    "rig": "TNG",
    "whatWasSeen": "Derrick inspection for heat and Potential falling objects",
    "whatWasDiscussed": "Check for radiated heat from flare on wires and cables in derrick",
    "whatWasReinforced": "Continue monitoring",
    "commentsAddedByRigLeadership": "Good focus and job done"
  },
  {
    "id": 92443,
    "date": "06.09.2026",
    "company": "Transocean",
    "rig": "TNG",
    "whatWasSeen": "DROPS sjekk i tavlerom 4",
    "whatWasDiscussed": "Ingen funn",
    "whatWasReinforced": ".",
    "commentsAddedByRigLeadership": ""
  },
  {
    "id": 92444,
    "date": "06.09.2026",
    "company": "Transocean",
    "rig": "TNG",
    "whatWasSeen": "Bra med barriærer på dekk",
    "whatWasDiscussed": "",
    "whatWasReinforced": "",
    "commentsAddedByRigLeadership": ""
  },
  {
    "id": 92445,
    "date": "06.09.2026",
    "company": "Transocean",
    "rig": "TNG",
    "whatWasSeen": "Inspeksjon av forskjellige nivå og utstyr i Derrick under well test",
    "whatWasDiscussed": "Jevnlig inspeksjon av varme på overflater i Derrick og på utstyr.",
    "whatWasReinforced": "Enige",
    "commentsAddedByRigLeadership": "God fokus og bra jobbet"
  },
  {
    "id": 92446,
    "date": "06.09.2026",
    "company": "Transocean",
    "rig": "TNG",
    "whatWasSeen": "Tok en tofs ved isolering av BOP UPS 2.",
    "whatWasDiscussed": "Infomere Subsea sup som forestående arbeid korrekt dokumentasjon ihht isolering Utføre isolering med tanke på bruk av rett PPE og følge FSE",
    "whatWasReinforced": "",
    "commentsAddedByRigLeadership": ""
  },
  {
    "id": 92447,
    "date": "06.09.2026",
    "company": "Transocean",
    "rig": "TNG",
    "whatWasSeen": "Well test. Hot surfaces",
    "whatWasDiscussed": "Heat on glas in aw cabin",
    "whatWasReinforced": "Scantec to adjust or rig up additional",
    "commentsAddedByRigLeadership": ""
  },
  {
    "id": 92448,
    "date": "06.09.2026",
    "company": "Transocean",
    "rig": "TNG",
    "whatWasSeen": "Flaring på bb brennerbom. Litt manglende deluge på brennerbom",
    "whatWasDiscussed": "Diskuterte mulighetene for å tilte ut ekstra kjøleskjold som er fastmonterte på brennerbom, for å introdusere mere vann og større vannskjold inn mot riggen",
    "whatWasReinforced": "Bcoleo leinng stopp i flaring etter en utilsiktet PSD1, som tillot oss å entre brennerbommer for å ta løs sikringer på kjøleskjold og folde de 90 grader ut fra bom. Resulterte i mye bedre kjøling og skjold når vi startet opp igjen. TNS - We ensure a common understanding",
    "commentsAddedByRigLeadership": ""
  },
  {
    "id": 92449,
    "date": "06.09.2026",
    "company": "Baker FES Slop",
    "rig": "TNG",
    "whatWasSeen": "God Kommunikasjon med Expro under overføring av slop til OTS Slop Unit, walked the line",
    "whatWasDiscussed": "",
    "whatWasReinforced": "",
    "commentsAddedByRigLeadership": ""
  },
  {
    "id": 92450,
    "date": "06.09.2026",
    "company": "Nov",
    "rig": "TNG",
    "whatWasSeen": "Subsea team carrying out function/pressure testing. Team carried out all pre checks and line tests before testing componnets.",
    "whatWasDiscussed": "Reinforced good practice, and all pre job checks.",
    "whatWasReinforced": "to continue as is",
    "commentsAddedByRigLeadership": ""
  },
  {
    "id": 92451,
    "date": "06.09.2026",
    "company": "Transocean",
    "rig": "TNG",
    "whatWasSeen": "vann kom inn i vinsjehus.",
    "whatWasDiscussed": "",
    "whatWasReinforced": "",
    "commentsAddedByRigLeadership": ""
  },
  {
    "id": 92452,
    "date": "06.09.2026",
    "company": "Transocean",
    "rig": "TNG",
    "whatWasSeen": "brief på helidekk før helikopterankomst",
    "whatWasDiscussed": "baggasjehåndtering, diskuterte mest ergonomisk og minst belastende måte å laste og losse baggasje og frakt på",
    "whatWasReinforced": "",
    "commentsAddedByRigLeadership": ""
  },
  {
    "id": 92453,
    "date": "06.09.2026",
    "company": "Transocean",
    "rig": "TNG",
    "whatWasSeen": "Det ble snakket om kropplassering i toolbox talk før oppstart. Arbeidet besto av arbeid med POD packers seal samt arbeid på boost line på riser. Det ble lagt god vekt på sikring av verktøy og utstyr, spesielt ved arbeid i høyden og over åpent område. Arbeidsområdet ble gjennomgått og holdt ryddig for å redusere risikoen for fallende gjenstander. Det var god kommunikasjon og involvering i teamet gjennom hele jobben.",
    "whatWasDiscussed": "",
    "whatWasReinforced": "",
    "commentsAddedByRigLeadership": ""
  },
  {
    "id": 92454,
    "date": "06.09.2026",
    "company": "Transocean",
    "rig": "TNG",
    "whatWasSeen": "Inspiserte ansvarsområdet for PFG",
    "whatWasDiscussed": "",
    "whatWasReinforced": "Fjerne kasse oppe på skap",
    "commentsAddedByRigLeadership": ""
  },
  {
    "id": 92455,
    "date": "06.09.2026",
    "company": "Transocean",
    "rig": "TNG",
    "whatWasSeen": "Good use of correct PPE",
    "whatWasDiscussed": "Follow procedures and have good communication",
    "whatWasReinforced": "Take a BRIEF if the task changes and re discuss the task",
    "commentsAddedByRigLeadership": "Good to hear that we have good routines."
  },
  {
    "id": 92456,
    "date": "06.09.2026",
    "company": "Transocean",
    "rig": "TNG",
    "whatWasSeen": "Åpning av sparkekant akterut på upper dekk for å draine ut vann ifm deluge",
    "whatWasDiscussed": "",
    "whatWasReinforced": "",
    "commentsAddedByRigLeadership": ""
  },
  {
    "id": 92457,
    "date": "06.09.2026",
    "company": "Transocean",
    "rig": "TNG",
    "whatWasSeen": "sjauing av utstyr på dekk.",
    "whatWasDiscussed": "passe på ergonomi, unngå ugunstig",
    "whatWasReinforced": "",
    "commentsAddedByRigLeadership": ""
  },
  {
    "id": 92458,
    "date": "06.09.2026",
    "company": "Transocean",
    "rig": "TNG",
    "whatWasSeen": "Arbeid med risers og justering av boost line. Sikring av verktøy og fallseler brukt ved arbeid i høyden. Vanskelig jobb å utføre, så det ble bestemt å få 6 stk løftet ned i treer bay for å få utført dette sikkert.",
    "whatWasDiscussed": "belastning på rygg",
    "whatWasReinforced": "",
    "commentsAddedByRigLeadership": ""
  },
  {
    "id": 92459,
    "date": "06.09.2026",
    "company": "Transocean",
    "rig": "TNG",
    "whatWasSeen": "Brukte riktige kjemikalie hansker i forbindelse med håndtering av kjølevæske.",
    "whatWasDiscussed": "",
    "whatWasReinforced": "",
    "commentsAddedByRigLeadership": ""
  },
  {
    "id": 92460,
    "date": "06.09.2026",
    "company": "rtc",
    "rig": "TNG",
    "whatWasSeen": "Kameratsjekk før jobb",
    "whatWasDiscussed": "",
    "whatWasReinforced": "",
    "commentsAddedByRigLeadership": ""
  },
  {
    "id": 92461,
    "date": "06.09.2026",
    "company": "GES",
    "rig": "TNG",
    "whatWasSeen": "Personnel high pressure washing on BOP in setback area. Chemical suit and goggles used, barriers in place and hose free of walkways",
    "whatWasDiscussed": "Good barrier management and planning",
    "whatWasReinforced": "Keep up good planning",
    "commentsAddedByRigLeadership": ""
  },
  {
    "id": 92462,
    "date": "06.09.2026",
    "company": "Transocean",
    "rig": "TNG",
    "whatWasSeen": "Arbeid med vaskemaskin i bysse",
    "whatWasDiscussed": "Brief før start",
    "whatWasReinforced": "",
    "commentsAddedByRigLeadership": ""
  },
  {
    "id": 92463,
    "date": "06.09.2026",
    "company": "Transocean",
    "rig": "TNG",
    "whatWasSeen": "Bytte ut Brine ventil",
    "whatWasDiscussed": "GBroudk palva nPleRgOgMinTg, -d kroerntere line. fokus på rett bruk av verktøy. Unngå fingerskader",
    "whatWasReinforced": ".",
    "commentsAddedByRigLeadership": "Godt jobbet"
  },
  {
    "id": 92464,
    "date": "06.09.2026",
    "company": "Transocean",
    "rig": "TNG",
    "whatWasSeen": "Flere mørke lamper i mekanisk verksted og i gangen på stbd. Byttet disse så ble det lyst og fint.",
    "whatWasDiscussed": "",
    "whatWasReinforced": "",
    "commentsAddedByRigLeadership": ""
  },
  {
    "id": 92465,
    "date": "06.09.2026",
    "company": "Transocean",
    "rig": "TNG",
    "whatWasSeen": "Gjennomgang av løfteplan sammen med pon power før løfting av ladeluftkjøler startet.",
    "whatWasDiscussed": "",
    "whatWasReinforced": "",
    "commentsAddedByRigLeadership": ""
  },
  {
    "id": 92466,
    "date": "06.09.2026",
    "company": "Subseaquence",
    "rig": "TNG",
    "whatWasSeen": "Observed men taking time to collect correct tools for task",
    "whatWasDiscussed": "Talked about checking prior during and after",
    "whatWasReinforced": "Agreement gained to do this everytime",
    "commentsAddedByRigLeadership": ""
  },
  {
    "id": 92467,
    "date": "06.09.2026",
    "company": "Wellpartner",
    "rig": "TNG",
    "whatWasSeen": "Respekterer rødsonen",
    "whatWasDiscussed": "",
    "whatWasReinforced": "",
    "commentsAddedByRigLeadership": ""
  },
  {
    "id": 92468,
    "date": "06.09.2026",
    "company": "Transocean",
    "rig": "TNG",
    "whatWasSeen": "rydding babord pontong",
    "whatWasDiscussed": "mye unødvendig rot",
    "whatWasReinforced": "folk må bli flinkere til og ta med ting",
    "commentsAddedByRigLeadership": ""
  },
  {
    "id": 92469,
    "date": "06.09.2026",
    "company": "Transocean",
    "rig": "TNG",
    "whatWasSeen": "working on riser with jacks.",
    "whatWasDiscussed": "kepp out of line of fire. use propper",
    "whatWasReinforced": "koepppp is hteadned sf ocrl eåa kr awshteil ed ejatc ikninn gi sliknaeps.",
    "commentsAddedByRigLeadership": ""
  },
  {
    "id": 92470,
    "date": "06.09.2026",
    "company": "Zeppelin",
    "rig": "TNG",
    "whatWasSeen": "Ryddet verktøy på plass etter endt jobb",
    "whatWasDiscussed": "ppe follow procedure.",
    "whatWasReinforced": "good communication while adjusting",
    "commentsAddedByRigLeadership": ""
  },
  {
    "id": 92471,
    "date": "06.09.2026",
    "company": "Transocean",
    "rig": "TNG",
    "whatWasSeen": "Rydding i ansvarsområde: Bosun store",
    "whatWasDiscussed": "Ordnet i verktøyene. Fjernet søppel og annet rot.",
    "whatWasReinforced": "Ryddig og rent område",
    "commentsAddedByRigLeadership": ""
  },
  {
    "id": 92472,
    "date": "06.09.2026",
    "company": "One subsea",
    "rig": "TNG",
    "whatWasSeen": "vasket og rengjorde i workshop og verifiserte god housekeeping",
    "whatWasDiscussed": "",
    "whatWasReinforced": "",
    "commentsAddedByRigLeadership": ""
  },
  {
    "id": 92473,
    "date": "06.09.2026",
    "company": "Transocean",
    "rig": "TNG",
    "whatWasSeen": "vasking i moonpool. riktig ppe blei brukt, og utstyr ryddet opp.",
    "whatWasDiscussed": "",
    "whatWasReinforced": "",
    "commentsAddedByRigLeadership": "God fokus og bra jobbet"
  },
  {
    "id": 92474,
    "date": "06.09.2026",
    "company": "Transocean",
    "rig": "TNG",
    "whatWasSeen": "Vasking i pumperom",
    "whatWasDiscussed": "Fokus på rett værneutstyr,",
    "whatWasReinforced": ".",
    "commentsAddedByRigLeadership": "God fokus og bra jobbet"
  },
  {
    "id": 92475,
    "date": "06.09.2026",
    "company": "Transocean",
    "rig": "TNG",
    "whatWasSeen": "Fant 3 blåsokker på gangvei.",
    "whatWasDiscussed": "Kaste og sortere søppel",
    "whatWasReinforced": "Kastet de i søpla. Byttet sekk i søppel bøtte og fraktet sekk til riktig avfall stasjon",
    "commentsAddedByRigLeadership": "Godt å høre at vi fokuserer på ren arbeidsplass. Bra jobbet."
  },
  {
    "id": 92476,
    "date": "06.09.2026",
    "company": "Transocean",
    "rig": "TNG",
    "whatWasSeen": "promt kort før løft med riserkran",
    "whatWasDiscussed": "",
    "whatWasReinforced": "",
    "commentsAddedByRigLeadership": ""
  },
  {
    "id": 92477,
    "date": "06.09.2026",
    "company": "Transocean",
    "rig": "TNG",
    "whatWasSeen": "Flytte om på risere fra styrbord til babord.",
    "whatWasDiscussed": "Gikk igjennom stikkordskort før vi startet jobben. Fokus på det som er nytt siden sist gang vi løftet på riserne: Nye sjøsikringsposter forut.",
    "whatWasReinforced": "Ble enige om å følge godt med på avstand mellom kran, risere og de nye postene. Utførte jobben ihht. planlegging.",
    "commentsAddedByRigLeadership": "Helt ihht Daily HSE Focus. Ch.M"
  },
  {
    "id": 92478,
    "date": "06.09.2026",
    "company": "Transocean",
    "rig": "TNG",
    "whatWasSeen": "Gas racks was observed on top of welder work shop while flaring during well test",
    "whatWasDiscussed": "To have these relocated when crane was available",
    "whatWasReinforced": "When flaring was stopped the gas racks was removed",
    "commentsAddedByRigLeadership": "God proaktiv aksjon under flaring. Ch.M"
  },
  {
    "id": 92479,
    "date": "06.09.2026",
    "company": "Transocean",
    "rig": "TNG",
    "whatWasSeen": "Lifting risers",
    "whatWasDiscussed": "TBT, banksman, promp card, barriers",
    "whatWasReinforced": "Som over",
    "commentsAddedByRigLeadership": ""
  },
  {
    "id": 92480,
    "date": "06.09.2026",
    "company": "Transocean",
    "rig": "TNG",
    "whatWasSeen": "løftet på slipjoint for å bistå subsea- avd",
    "whatWasDiscussed": "hva de ønsket å få gjort",
    "whatWasReinforced": "Holde avstand til last",
    "commentsAddedByRigLeadership": ""
  },
  {
    "id": 92481,
    "date": "06.09.2026",
    "company": "Transocean",
    "rig": "TNG",
    "whatWasSeen": "*Lakk vann inn i BB ankervinsj fra delugen mellom bua og skottet ifm brenning *Sugd opp vannet og lagt inn litt tek7 for å tette",
    "whatWasDiscussed": "",
    "whatWasReinforced": "",
    "commentsAddedByRigLeadership": "God observasjon og aksjon under flaring. Ch.M"
  },
  {
    "id": 92482,
    "date": "06.09.2026",
    "company": "Transocean",
    "rig": "TNG",
    "whatWasSeen": "A fire extinguisher was found obstructed, covered with various materials, making it difficult to see and access.",
    "whatWasDiscussed": "Discussed the importance of keeping all safety equipment fully visible and unobstructed to ensure quick access in an emergency.",
    "whatWasReinforced": "The materials were removed, and we agreed to keep the area clear moving forward to maintain proper visibility and accessibility of the extinguisher.",
    "commentsAddedByRigLeadership": ""
  },
  {
    "id": 92483,
    "date": "06.09.2026",
    "company": "Transocean",
    "rig": "TNG",
    "whatWasSeen": "Ansvarsområde OK !",
    "whatWasDiscussed": "",
    "whatWasReinforced": "",
    "commentsAddedByRigLeadership": ""
  },
  {
    "id": 92484,
    "date": "06.09.2026",
    "company": "RTC Offshore",
    "rig": "TNG",
    "whatWasSeen": "Bra handover, SJA møte og toolbox snakk før start av arbeid",
    "whatWasDiscussed": "",
    "whatWasReinforced": "",
    "commentsAddedByRigLeadership": ""
  },
  {
    "id": 92485,
    "date": "06.09.2026",
    "company": "oceaneering",
    "rig": "TNG",
    "whatWasSeen": "Brukte dobbelt hørselvern ute på dekk for å verne mot høy støy fra testanlegg og redusere risikoen for hørselskade",
    "whatWasDiscussed": "",
    "whatWasReinforced": "",
    "commentsAddedByRigLeadership": "Helt ihht Daily HSE Focus. Ch.M"
  },
  {
    "id": 92486,
    "date": "06.09.2026",
    "company": "Aramark",
    "rig": "TNG",
    "whatWasSeen": "Dørliste ved gulv har løsnet i silent room.",
    "whatWasDiscussed": "snubblefare",
    "whatWasReinforced": "",
    "commentsAddedByRigLeadership": ""
  },
  {
    "id": 92487,
    "date": "06.09.2026",
    "company": "Transocean",
    "rig": "TNG",
    "whatWasSeen": "Excellent handover from offgoing deck crew to oncoming deck crew regarding current well test operation regarding fireguard information, transfer of knowledge is always appreciated.",
    "whatWasDiscussed": "",
    "whatWasReinforced": "",
    "commentsAddedByRigLeadership": ""
  },
  {
    "id": 92488,
    "date": "06.09.2026",
    "company": "Transocean",
    "rig": "TNG",
    "whatWasSeen": "Flammesensor på welltest-område aktivert ved oppstart av fakling",
    "whatWasDiscussed": "Sensoe var inhibitert i henhold til plan, og alarmen gikk derfor ikke ut på riggen. Tok kontakt med personnel i området for å få bekreftet alt OK.",
    "whatWasReinforced": "Rask respons fra operatør som bekreftet alt ok og at sensor var aktivert av flamme på brennerbom.",
    "commentsAddedByRigLeadership": "God aksjon og rask respons. Ch.M"
  },
  {
    "id": 92489,
    "date": "06.09.2026",
    "company": "Transocean",
    "rig": "TNG",
    "whatWasSeen": "Før oppstart av brønntesting, hadde sjefselektriker og maskinsjef en omfattende og god gjennomgang av inhibiteringene på \"K-Safe\".",
    "whatWasDiscussed": "Rasjonalet bak en del av inhibiteringene ble gjennnomgått i deltalj. Etter dette oppnådde vi felles forståelse.",
    "whatWasReinforced": "Å fortsette på dette arbeidet gode arbeidet.",
    "commentsAddedByRigLeadership": ""
  },
  {
    "id": 92490,
    "date": "06.09.2026",
    "company": "Transocean",
    "rig": "TNG",
    "whatWasSeen": "Før well testing skulle vi legge ut HC, H2S, Flamme og Heat sensorer",
    "whatWasDiscussed": "Hvilkne meldere som skulle bli lagt ut helt og hvilkne meldere som skulle bli lagt ut delvis",
    "whatWasReinforced": "Når vi får alarm / warning så skulle det sjekkes ut med engang man får indukasjon",
    "commentsAddedByRigLeadership": ""
  },
  {
    "id": 92491,
    "date": "06.09.2026",
    "company": "Transocean",
    "rig": "TNG",
    "whatWasSeen": "God gjennomgang.",
    "whatWasDiscussed": "Representant fra Well Partner var i driller bua og vi gikk gjennom prosedyren for Wellsafe Enabler system og litt hvordan den virker. God og nyttig gjennomgang.",
    "whatWasReinforced": "",
    "commentsAddedByRigLeadership": "Godt å høre. Kunnskaps overføring gjør oss alle bedre."
  },
  {
    "id": 92492,
    "date": "06.09.2026",
    "company": "One subsea",
    "rig": "TNG",
    "whatWasSeen": "God handover",
    "whatWasDiscussed": "",
    "whatWasReinforced": "",
    "commentsAddedByRigLeadership": ""
  },
  {
    "id": 92493,
    "date": "06.09.2026",
    "company": "Scan tech",
    "rig": "TNG",
    "whatWasSeen": "God handover",
    "whatWasDiscussed": "",
    "whatWasReinforced": "",
    "commentsAddedByRigLeadership": ""
  },
  {
    "id": 92494,
    "date": "06.09.2026",
    "company": "One subsea",
    "rig": "TNG",
    "whatWasSeen": "God handover fra dagskift",
    "whatWasDiscussed": "",
    "whatWasReinforced": "",
    "commentsAddedByRigLeadership": ""
  },
  {
    "id": 92495,
    "date": "06.09.2026",
    "company": "Transocean",
    "rig": "TNG",
    "whatWasSeen": "God kommunikasjon under streiferunde i teknisk område ved flaring.",
    "whatWasDiscussed": "",
    "whatWasReinforced": "",
    "commentsAddedByRigLeadership": ""
  },
  {
    "id": 92496,
    "date": "06.09.2026",
    "company": "Harbour",
    "rig": "TNG",
    "whatWasSeen": "God planlegging/plan for backload av 3 risere fra rigg til båt- her er det flere hensyn og ta ihht WL operasjonen ombord samt fartøy som må ligge med styrhuset forut grunnet flammebom.",
    "whatWasDiscussed": "",
    "whatWasReinforced": "",
    "commentsAddedByRigLeadership": ""
  },
  {
    "id": 92497,
    "date": "06.09.2026",
    "company": "Expro",
    "rig": "TNG",
    "whatWasSeen": "God TBT før opning av brønn",
    "whatWasDiscussed": "Det blei diskutert farer og oppgaver",
    "whatWasReinforced": "",
    "commentsAddedByRigLeadership": ""
  },
  {
    "id": 92498,
    "date": "06.09.2026",
    "company": "Expro",
    "rig": "TNG",
    "whatWasSeen": "Good communication during flowing operations",
    "whatWasDiscussed": "Cblhaenct koipnpge orant øMreegn epump",
    "whatWasReinforced": "One man to monitor Meg injection. Thanks",
    "commentsAddedByRigLeadership": ""
  },
  {
    "id": 92499,
    "date": "06.09.2026",
    "company": "Transocean",
    "rig": "TNG",
    "whatWasSeen": "Handover",
    "whatWasDiscussed": "Fortalt hva som hadde skjedd",
    "whatWasReinforced": "Følge med på sensorer, varsle om",
    "commentsAddedByRigLeadership": ""
  },
  {
    "id": 92500,
    "date": "06.09.2026",
    "company": "Expro",
    "rig": "TNG",
    "whatWasSeen": "Handover",
    "whatWasDiscussed": "Gigjoedn nhoamnd noavtetre n o, gh vtoal lsboomx t asklku flløer skje igansetting av skift og prøvetaking",
    "whatWasReinforced": "Hmvaond faånr uvit sslkaagl pgåjø nreo ejonb abve nm -esladfeer noeg trykt",
    "commentsAddedByRigLeadership": ""
  },
  {
    "id": 92501,
    "date": "06.09.2026",
    "company": "oceaneering",
    "rig": "TNG",
    "whatWasSeen": "Har fått beskjed om at det vil bli høyt lydnivå/støy under deler av testingen. Hentet derfor inn plugger i kontrollrom Hadde samtale i crew om det å ha plugger med seg når en beveger seg ute på riggen. En kan da etablere dobbelt hørselsvern ved behov",
    "whatWasDiscussed": "",
    "whatWasReinforced": "",
    "commentsAddedByRigLeadership": "Helt ihht Daily HSE Focus. Ch.M"
  },
  {
    "id": 92502,
    "date": "06.09.2026",
    "company": "Harbour Energy",
    "rig": "TNG",
    "whatWasSeen": "HSE focus during well clean up - Communication.",
    "whatWasDiscussed": "Excellent communication and coordination between all personnel involved in the well test operation, including Expro, Driller, Bridge, and supporting teams. Clear and timely communication ensured a shared understanding of ongoing activities, operational status, and potential changes.",
    "whatWasReinforced": "Strong teamwork and collaboration contributed to a safe and efficient execution of the operation.",
    "commentsAddedByRigLeadership": ""
  },
  {
    "id": 92503,
    "date": "06.09.2026",
    "company": "Transocean",
    "rig": "TNG",
    "whatWasSeen": "I dag hadde vi en ny gjennomgang av oppsettet på \"K-Safe\" i forbindelse med brønntesting. Rasjonalet bak inhibiteringene ble ytterligere elaborert.",
    "whatWasDiscussed": "Diskusjonen gikk rundt det at det oppsettet vi hadde var for konservativt.",
    "whatWasReinforced": "Endringer i oppsettet er på beddingen, og vil bli gjennomført straks det endelige oppsettet foreligger. Bred konsensus rundt dette ble etablert.",
    "commentsAddedByRigLeadership": ""
  },
  {
    "id": 92504,
    "date": "06.09.2026",
    "company": "Transocean",
    "rig": "TNG",
    "whatWasSeen": "Inspeksjon av AW og viftehus i forbindelse med vann fra deluge under brønntesting",
    "whatWasDiscussed": "Kom vann inn i bb aktre AW hus på grunn av en gummipakning som lakk.",
    "whatWasReinforced": "Dekk fikk tettet så godt de kunne, og sugd ut vannet med en fatstøvsuger. Deluge fra brennebom står rett på AW hus, så vanskelig å unngå at ikke noe vann kommer inn. Etter modifikasjonen kommer det bare minimalt inn i AW huset.",
    "commentsAddedByRigLeadership": "God observasjon og aksjon under flaring. Ch.M"
  },
  {
    "id": 92505,
    "date": "06.09.2026",
    "company": "Transocean",
    "rig": "TNG",
    "whatWasSeen": "Kommunikasjonsprotokollen ble fulgt til punkt og prikke under kommunikasjonen mellom Expro og broen under faklingen i dag. Felles forståelse var gjennomgangstonen.",
    "whatWasDiscussed": "Hvor viktig god og utvetydig kommunikasjon er under den operasjonen vi gjennomfører nå.",
    "whatWasReinforced": "Å holde frem som vi stevner.",
    "commentsAddedByRigLeadership": ""
  },
  {
    "id": 92506,
    "date": "06.09.2026",
    "company": "Engage",
    "rig": "TNG",
    "whatWasSeen": "Korrekt bruk av ppe ved prøvetaking av hydrocarboner i brønntest",
    "whatWasDiscussed": "PPE",
    "whatWasReinforced": "Prompt card, bruk av ppe",
    "commentsAddedByRigLeadership": ""
  },
  {
    "id": 92507,
    "date": "06.09.2026",
    "company": "Zeppelin",
    "rig": "TNG",
    "whatWasSeen": "Løft av ette kjøler etter plan",
    "whatWasDiscussed": "Stå på siker plass",
    "whatWasReinforced": "Stenge av maskinrom under løft.",
    "commentsAddedByRigLeadership": ""
  },
  {
    "id": 92508,
    "date": "06.09.2026",
    "company": "Expro",
    "rig": "TNG",
    "whatWasSeen": "Observerte en lite lekkasje på en kobling mellom 2 synflexslanger under gating. Dette ble observert en halvtime før halv 5 da vi skulle starte opp flowen fra brønnen igjen. Lekkasjen ble fikset.",
    "whatWasDiscussed": "",
    "whatWasReinforced": "",
    "commentsAddedByRigLeadership": "God observasjon og aksjon. Ch.M"
  },
  {
    "id": 92509,
    "date": "06.09.2026",
    "company": "Transocean",
    "rig": "TNG",
    "whatWasSeen": "På broen hadde vi i dag en god gjennomgang av \"WSOC\" dokumentet for IRPA. Punkt for punkt gikk vi gjennom alle aspekt av teksten og felles forståelse ble etablert på en bred basis.",
    "whatWasDiscussed": "Nytten av en slik gjennomgang kom klart frem, når behovet for endringer av detaljer materialserte seg.",
    "whatWasReinforced": "Å fortsette dette gode arbeidet.",
    "commentsAddedByRigLeadership": ""
  },
  {
    "id": 92510,
    "date": "06.09.2026",
    "company": "Baker",
    "rig": "TNG",
    "whatWasSeen": "PDO sjekk",
    "whatWasDiscussed": "",
    "whatWasReinforced": "",
    "commentsAddedByRigLeadership": ""
  },
  {
    "id": 92511,
    "date": "06.09.2026",
    "company": "Zeppelin",
    "rig": "TNG",
    "whatWasSeen": "Riktig løfteutstyr",
    "whatWasDiscussed": "Arb i hht til arb plan",
    "whatWasReinforced": "Arb ihht arb plan",
    "commentsAddedByRigLeadership": ""
  },
  {
    "id": 92512,
    "date": "06.09.2026",
    "company": "Transocean",
    "rig": "TNG",
    "whatWasSeen": "Riktig ppe og verktøy, Ble brukt når i byttet ventil i mud pumperom. Promt kort gjennom gått før jobb startet. Arbeids-plass ryddet etter endt jobb.",
    "whatWasDiscussed": "PPE",
    "whatWasReinforced": "Følg plan",
    "commentsAddedByRigLeadership": "God fokus og bra jobbet."
  },
  {
    "id": 92513,
    "date": "06.09.2026",
    "company": "oceaneering",
    "rig": "TNG",
    "whatWasSeen": "ROV skulle observere HSLV på 50m vanndyp under testing av brønnen",
    "whatWasDiscussed": "Hvor vill strømmen ta ROV om en skulle miste link til OROC, eller om noe uforutsett skulle skje pga testing",
    "whatWasReinforced": "Plassere ROV nedstrøms for riser/HSLV. ROV vil da drifte bort ifra Riser/HSLV om vi skulle miste kontroll",
    "commentsAddedByRigLeadership": ""
  },
  {
    "id": 92514,
    "date": "06.09.2026",
    "company": "Altus",
    "rig": "TNG",
    "whatWasSeen": "Sikret wireline kabel inntill rekverk",
    "whatWasDiscussed": "",
    "whatWasReinforced": "",
    "commentsAddedByRigLeadership": ""
  },
  {
    "id": 92515,
    "date": "06.09.2026",
    "company": "Transocean",
    "rig": "TNG",
    "whatWasSeen": "Skryt til Harbour for god Welltest presentasjon på velkommen ombord møte. Informativ og effektiv gjennomgang.",
    "whatWasDiscussed": "",
    "whatWasReinforced": "",
    "commentsAddedByRigLeadership": "Godt å høre. God erfaringsoverføring gjør oss alle bedre."
  },
  {
    "id": 92516,
    "date": "06.09.2026",
    "company": "Transocean",
    "rig": "TNG",
    "whatWasSeen": "TBT utført i helibua før lossing og lasting helikopter LN-OMV",
    "whatWasDiscussed": "",
    "whatWasReinforced": "",
    "commentsAddedByRigLeadership": ""
  },
  {
    "id": 92517,
    "date": "06.09.2026",
    "company": "Aramark",
    "rig": "TNG",
    "whatWasSeen": "Thanks to Technical for fixing the arm in dishwasher machine",
    "whatWasDiscussed": "",
    "whatWasReinforced": "",
    "commentsAddedByRigLeadership": ""
  },
  {
    "id": 92518,
    "date": "06.09.2026",
    "company": "oceaneering",
    "rig": "TNG",
    "whatWasSeen": "Tok en gjennomgang på skiftet om oppgaver, rømningsveier og kommunikasjon MHT. testing av brønn",
    "whatWasDiscussed": "",
    "whatWasReinforced": "",
    "commentsAddedByRigLeadership": ""
  },
  {
    "id": 92519,
    "date": "06.09.2026",
    "company": "Expro",
    "rig": "TNG",
    "whatWasSeen": "Toolbox talk før åpning av brønn.",
    "whatWasDiscussed": "Faremomenter og bruk av riktig ppe.",
    "whatWasReinforced": "",
    "commentsAddedByRigLeadership": ""
  },
  {
    "id": 92520,
    "date": "06.09.2026",
    "company": "Expro",
    "rig": "TNG",
    "whatWasSeen": "Training equipment was left on the gym floor, creating a potential trip hazard.",
    "whatWasDiscussed": "No discussion required. Immediate housekeeping action taken.",
    "whatWasReinforced": "Removed training equipment left on the gym floor to reduce trip hazards and improve housekeeping.",
    "commentsAddedByRigLeadership": ""
  },
  {
    "id": 92521,
    "date": "06.09.2026",
    "company": "Aramark",
    "rig": "TNG",
    "whatWasSeen": "Tusen takk til Anders som tok ut søpla for meg i natt 😊 Det er 👍 opp .",
    "whatWasDiscussed": "",
    "whatWasReinforced": "",
    "commentsAddedByRigLeadership": ""
  },
  {
    "id": 92522,
    "date": "06.09.2026",
    "company": "Harbour Energy",
    "rig": "TNG",
    "whatWasSeen": "Verified with NTP, WT supervisor and bridge regarding wind criteria for flaring. Verified forecast with Storm Geo duty and decided to shut-it well.",
    "whatWasDiscussed": "Wind criteria, period of low wind vs forecast.",
    "whatWasReinforced": "Agreed to follow the DOP and criteria set for flaring. Monitored wind continuously and agreed to meet again to assess evy 30 min.",
    "commentsAddedByRigLeadership": ""
  },
  {
    "id": 92523,
    "date": "06.09.2026",
    "company": "Transocean",
    "rig": "TNG",
    "whatWasSeen": "Vindkriterier for fakling",
    "whatWasDiscussed": "Vindstyrke- og retning marginal ift kriterier for fakling.",
    "whatWasReinforced": "Oppdaterte Expro fortløpende om vindforhold, som igjen avbrøt fakling.",
    "commentsAddedByRigLeadership": ""
  },
  {
    "id": 92524,
    "date": "06.09.2026",
    "company": "Harbour Energy",
    "rig": "TNG",
    "whatWasSeen": "Went through the well control actions with Driller, AD and NTP on night shift prior to start well clean up to ensure a common understanding of the different roles and responsibilities - as per The Norge Standard.",
    "whatWasDiscussed": "Discussed the different scenarios, flow charts and actions to take.",
    "whatWasReinforced": "",
    "commentsAddedByRigLeadership": ""
  },
  {
    "id": 92525,
    "date": "06.09.2026",
    "company": "Halliburton",
    "rig": "TNG",
    "whatWasSeen": "When arriving to the rig, an overview of ongoing well test ops was given by DSV.",
    "whatWasDiscussed": "Particular focus on barriers and safety valves in case of emergency, plus shutdown procedure. Good explanation for arriving personnel of how operational safety is being managed.",
    "whatWasReinforced": "Increased awareness for the arriving personnel.",
    "commentsAddedByRigLeadership": ""
  },
  {
    "id": 92526,
    "date": "06.09.2026",
    "company": "Harbour",
    "rig": "TNG",
    "whatWasSeen": "Familarisering med shut down systemer og well control action plans for clean up - gjennomgang med drill crew",
    "whatWasDiscussed": "Familarisering av shut down system og hva skjer Well control aksjons planer og diskusjon på hvordan håndtere og",
    "whatWasReinforced": "Økt forståelse for systemer og hvordan respondere - Godt engasjement av drill crew",
    "commentsAddedByRigLeadership": ""
  },
  {
    "id": 92527,
    "date": "06.09.2026",
    "company": "Transocean",
    "rig": "TNG",
    "whatWasSeen": "God gjennomgang av senarioer med tanke på lekasje på forskjellige plasser, med tanke på flering. Og hva vi skal gjøre i disse senarioene.",
    "whatWasDiscussed": "Følge well control flow chart. Samt ha bekreftende kommunikajon.",
    "whatWasReinforced": "",
    "commentsAddedByRigLeadership": "Godt å høre at vi har god fokus."
  },
  {
    "id": 92528,
    "date": "06.09.2026",
    "company": "Transocean",
    "rig": "TNG",
    "whatWasSeen": "God kommunikasjon på boredekk",
    "whatWasDiscussed": "",
    "whatWasReinforced": "",
    "commentsAddedByRigLeadership": "One Team"
  },
  {
    "id": 92529,
    "date": "06.09.2026",
    "company": "OneSubsea",
    "rig": "TNG",
    "whatWasSeen": "TBT on drillfloor",
    "whatWasDiscussed": "Attend toolbox on drillfloor",
    "whatWasReinforced": "",
    "commentsAddedByRigLeadership": ""
  },
  {
    "id": 92530,
    "date": "06.09.2026",
    "company": "Transocean",
    "rig": "TNG",
    "whatWasSeen": "testkjøring av Riser catwalk",
    "whatWasDiscussed": "kommunikasjon mellom drillerbu og",
    "whatWasReinforced": "",
    "commentsAddedByRigLeadership": "God fokus og bra jobbet."
  },
  {
    "id": 92531,
    "date": "06.09.2026",
    "company": "Transocean",
    "rig": "TNG",
    "whatWasSeen": "Vasking på boredekk og områder rundt.",
    "whatWasDiscussed": "Vhyikdtmigehceten med riktig bruk av PPE.",
    "whatWasReinforced": ".",
    "commentsAddedByRigLeadership": "Godt å høre at vi har gode rutiner."
  },
  {
    "id": 92532,
    "date": "06.09.2026",
    "company": "GES",
    "rig": "TNG",
    "whatWasSeen": "discussed what tools were required for the job",
    "whatWasDiscussed": "used the correct tools for job so i can be done safely",
    "whatWasReinforced": "all tools were inspected before use",
    "commentsAddedByRigLeadership": "No"
  },
  {
    "id": 92533,
    "date": "06.09.2026",
    "company": "OneSubsea",
    "rig": "TNG",
    "whatWasSeen": "TBT for re-dress TH plugs",
    "whatWasDiscussed": "Bruk av dedikerte tools og tegning",
    "whatWasReinforced": "Følg prosedyrer og tegninger",
    "commentsAddedByRigLeadership": ""
  },
  {
    "id": 92534,
    "date": "06.09.2026",
    "company": "Transocean",
    "rig": "TNG",
    "whatWasSeen": ".",
    "whatWasDiscussed": "Gikk mellom plan, opplining samt hvilke resurser som må være tilgjengelige",
    "whatWasReinforced": "Planlegge pauser/lunch med sementer i forkant",
    "commentsAddedByRigLeadership": "God fokus. God planlegging er nøkkelen til sukse."
  },
  {
    "id": 92535,
    "date": "06.09.2026",
    "company": "Transocean",
    "rig": "TNG",
    "whatWasSeen": "gjenomgang av diverse senarioer og de forskjellinge ned stengings systemene",
    "whatWasDiscussed": ".",
    "whatWasReinforced": ".",
    "commentsAddedByRigLeadership": "Godt å høre. God erfaringsoverføring gjør oss alle bedre."
  },
  {
    "id": 92536,
    "date": "06.09.2026",
    "company": "One subsea",
    "rig": "TNG",
    "whatWasSeen": "God kommunikasjon med DF under oppstart av brønn.",
    "whatWasDiscussed": "",
    "whatWasReinforced": "",
    "commentsAddedByRigLeadership": ""
  },
  {
    "id": 92537,
    "date": "06.09.2026",
    "company": "Transocean",
    "rig": "TNG",
    "whatWasSeen": "Hadde brief på bro med gjennomgang av hvilke del av brann og gass som er utkoplet isammenheng med testen",
    "whatWasDiscussed": "",
    "whatWasReinforced": "",
    "commentsAddedByRigLeadership": ""
  },
  {
    "id": 92538,
    "date": "06.09.2026",
    "company": "Transocean",
    "rig": "TNG",
    "whatWasSeen": "Handover fra nattskift",
    "whatWasDiscussed": "God handover fra nattskift med relevant info om pågående operasjon",
    "whatWasReinforced": "Sikrer effektiv og sikker drift.",
    "commentsAddedByRigLeadership": ""
  },
  {
    "id": 92539,
    "date": "06.09.2026",
    "company": "Transocean",
    "rig": "TNG",
    "whatWasSeen": "Inhibitering ifm brønntest",
    "whatWasDiscussed": "Gjennomgang av inhibiteringsplan, brief på bro med teknisk, med informasjon om status i tekniske områder, og bortfall av automatiske effekter ved alarm.",
    "whatWasReinforced": "",
    "commentsAddedByRigLeadership": ""
  },
  {
    "id": 92540,
    "date": "06.09.2026",
    "company": "Transocean",
    "rig": "TNG",
    "whatWasSeen": "while carrying out checks discovered the exhaust had blowen of one of the glycol pumps",
    "whatWasDiscussed": "informed expro",
    "whatWasReinforced": "Expro were straight up to assist reinstalling the exhaust",
    "commentsAddedByRigLeadership": "Good focus and action taken."
  },
  {
    "id": 92541,
    "date": "06.09.2026",
    "company": "Transocean",
    "rig": "TNG",
    "whatWasSeen": "Inspeksjon i derrick",
    "whatWasDiscussed": "Se etter pfg",
    "whatWasReinforced": "OK",
    "commentsAddedByRigLeadership": ""
  }
]